{
  "sections": {
    "main": {
      "type": "main-page",
      "disabled": true,
      "settings": { "padding_top": 28, "padding_bottom": 28 }
    },
    "main_portada_unicolumna_xwrrPf": {
      "type": "main-portada-unicolumna",
      "settings": {
        "altura_contenedor": 640,
        "usar_video_fondo": false,
        "link_video_fondo": "",
        "habilitar_sonido_video": false,
        "mostrar_switch_sonido": true,
        "activar_filtro_video": true,
        "grados_filtro": 180,
        "primer_color_filtro": "#2a7b9b",
        "opacidad_primer_color": 1,
        "segundo_color_filtro": "#eddd53",
        "opacidad_segundo_color": 0,
        "imagen_fondo_desktop": "shopify:\/\/shop_images\/3O7A1212.jpg",
        "imagen_fondo_tablet": "shopify:\/\/shop_images\/3O7A1212.jpg",
        "imagen_fondo_mobile": "shopify:\/\/shop_images\/3O7A1212.jpg",
        "color_fondo_contenedor": "#f5f5f5",
        "color_contenedor": "#c9a76d",
        "fondo_transparente": true,
        "ancho_contenedor": 650,
        "titulo": "From Our Farm Yards to Your Back Yards",
        "clase_titulo": "Titulo-Nickson-four-h1-portada",
        "color_titulo": "#ffffff",
        "subtitulo": "",
        "clase_subtitulo": "Titulo-Nickson-six-h2-portada",
        "color_subtitulo": "#c9a76d",
        "texto": "",
        "color_texto": "#666666",
        "ocultar_botones": true,
        "mostrar_dos_botones": false,
        "texto_boton_1": "Shop Now →",
        "enlace_boton_1": "",
        "color_boton_1": "#002554",
        "color_texto_boton_1": "#ffffff",
        "boton_1_transparente": false,
        "texto_boton_2": "Learn more",
        "enlace_boton_2": "",
        "color_boton_2": "#002554",
        "color_texto_boton_2": "#002554",
        "boton_2_transparente": true
      }
    },
    "main_coleccion_de_productos_Jc3pRG": {
      "type": "main-coleccion-de-productos",
      "disabled": true,
      "settings": {
        "background_color": "#002554",
        "titulo": "Gift Boxes",
        "clase_titulo": "Titulo-Nickson-six-h1",
        "color_titulo": "#fff9f1",
        "texto": "<p>Browse  curated selections of our finest cheeses including classic favorites that are perfect for any occasion.<\/p>",
        "color_texto": "#fff9f1",
        "ocultar_botones": true,
        "mostrar_dos_botones": false,
        "texto_boton_1": "See All Products  →",
        "enlace_boton_1": "",
        "color_boton_1": "#002554",
        "color_texto_boton_1": "#ffffff",
        "boton_1_transparente": false,
        "texto_boton_2": "Contact",
        "enlace_boton_2": "",
        "color_boton_2": "#002554",
        "color_texto_boton_2": "#002554",
        "boton_2_transparente": true,
        "collection": "rumiano-holiday",
        "columns": 3,
        "rows": 2,
        "producto-provedor": "#c9a76d",
        "producto-titulo": "#fff9f1",
        "clase_titulo_productos": "Titulo-Nickson-six-h6",
        "producto-categoria": "#c9a76d",
        "color_precio_producto": "#fff9f1",
        "producto-peso": "#002554",
        "color_descripcion_producto": "#fff9f1",
        "color_boton_ver": "#002554",
        "color_texto_boton_ver": "#002554",
        "boton_ver_transparente": true,
        "ocultar_boton_ver": true,
        "texto_boton_wheretobuy": "Where to buy",
        "text_button_addtocart": "Add to Cart",
        "enlace_boton_wheretobuy": "",
        "color_boton_wheretobuy": "#002554",
        "color_texto_boton_wheretobuy": "#ffffff",
        "boton_wheretobuy_transparente": false,
        "color_boton_agregar": "#002554",
        "color_texto_boton_agregar": "#ffffff",
        "boton_agregar_transparente": false,
        "transparent_cards": true,
        "card_background_color": "#f5f5f5"
      }
    },
    "main_slider_animado_logos_eDDnQ3": {
      "type": "main-slider-animado-logos",
      "blocks": {
        "bloque_multicolumna_9Mkkqe": {
          "type": "bloque_multicolumna",
          "settings": {
            "block_id": "",
            "block_visible": true,
            "top_image": "shopify:\/\/shop_images\/Bristol_Farm.png"
          }
        },
        "bloque_multicolumna_xD8UkH": {
          "type": "bloque_multicolumna",
          "settings": {
            "block_id": "",
            "block_visible": true,
            "top_image": "shopify:\/\/shop_images\/Fresh_Tyme.png"
          }
        },
        "bloque_multicolumna_pF969G": {
          "type": "bloque_multicolumna",
          "settings": {
            "block_id": "",
            "block_visible": true,
            "top_image": "shopify:\/\/shop_images\/Jimbos.png"
          }
        },
        "bloque_multicolumna_nLYKNn": {
          "type": "bloque_multicolumna",
          "settings": {
            "block_id": "",
            "block_visible": true,
            "top_image": "shopify:\/\/shop_images\/Lazy_a_cres.png"
          }
        },
        "bloque_multicolumna_ynQPYj": {
          "type": "bloque_multicolumna",
          "settings": {
            "block_id": "",
            "block_visible": true,
            "top_image": "shopify:\/\/shop_images\/Market_of_choice.png"
          }
        },
        "bloque_multicolumna_KCjJin": {
          "type": "bloque_multicolumna",
          "settings": {
            "block_id": "",
            "block_visible": true,
            "top_image": "shopify:\/\/shop_images\/Mom.png"
          }
        },
        "bloque_multicolumna_UyiFpT": {
          "type": "bloque_multicolumna",
          "settings": {
            "block_id": "",
            "block_visible": true,
            "top_image": "shopify:\/\/shop_images\/Natural_groces.png"
          }
        },
        "bloque_multicolumna_VLwN6K": {
          "type": "bloque_multicolumna",
          "settings": {
            "block_id": "",
            "block_visible": true,
            "top_image": "shopify:\/\/shop_images\/Poc.png"
          }
        },
        "bloque_multicolumna_kfH8kg": {
          "type": "bloque_multicolumna",
          "settings": {
            "block_id": "",
            "block_visible": true,
            "top_image": "shopify:\/\/shop_images\/Raleys.png"
          }
        },
        "bloque_multicolumna_m73nFA": {
          "type": "bloque_multicolumna",
          "settings": {
            "block_id": "",
            "block_visible": true,
            "top_image": "shopify:\/\/shop_images\/Sprouds_farmers.png"
          }
        },
        "bloque_multicolumna_CrGqTk": {
          "type": "bloque_multicolumna",
          "settings": {
            "block_id": "",
            "block_visible": true,
            "top_image": "shopify:\/\/shop_images\/Whole_foods.png"
          }
        }
      },
      "block_order": [
        "bloque_multicolumna_9Mkkqe",
        "bloque_multicolumna_xD8UkH",
        "bloque_multicolumna_pF969G",
        "bloque_multicolumna_nLYKNn",
        "bloque_multicolumna_ynQPYj",
        "bloque_multicolumna_KCjJin",
        "bloque_multicolumna_UyiFpT",
        "bloque_multicolumna_VLwN6K",
        "bloque_multicolumna_kfH8kg",
        "bloque_multicolumna_m73nFA",
        "bloque_multicolumna_CrGqTk"
      ],
      "disabled": true,
      "settings": {
        "background_color": "#002554",
        "enable_background_image": false,
        "titulo": "Available At",
        "clase_titulo": "Titulo-Nickson-four-h1",
        "color_titulo": "#fafbfc",
        "padding_top": 40,
        "padding_sides": 20,
        "columns_desktop": 7,
        "tag_mostrar": "",
        "tag_ocultar": ""
      }
    },
    "main_contenedor_titular_cuerpo_unicolumna_dQfyUk": {
      "type": "main-contenedor-titular-cuerpo-unicolumna",
      "disabled": true,
      "settings": {
        "background_color": "#fff9f1",
        "habilitar_imagen_fondo": false,
        "padding_top": 45,
        "padding_bottom": 20,
        "titulo": "Rumiano Organic Products",
        "clase_titulo": "Titulo-Nickson-six-h1",
        "color_titulo": "#002554",
        "ocultar_subtito": true,
        "subtitulo": "Better for You",
        "clase_subtitulo": "Titulo-Nickson-six-h2",
        "color_subtitulo": "#c9a76d",
        "texto": "<p>From artisanal cheeses to thoughtful gifts and merchandise, there’s something for everyone.<\/p>",
        "color_texto": "#002554",
        "ocultar_botones": true,
        "mostrar_dos_botones": false,
        "texto_boton_1": "Explore our impact  →",
        "enlace_boton_1": "",
        "color_boton_1": "#002554",
        "color_texto_boton_1": "#ffffff",
        "boton_1_transparente": false,
        "texto_boton_2": "Contact",
        "enlace_boton_2": "",
        "color_boton_2": "#002554",
        "color_texto_boton_2": "#002554",
        "boton_2_transparente": true
      }
    },
    "main_contenedor_multicolumnas_bloques_wbjfPR": {
      "type": "main-contenedor-multicolumnas-bloques",
      "blocks": {
        "bloque_multicolumna_CFeDCx": {
          "type": "bloque_multicolumna",
          "settings": {
            "top_image": "shopify:\/\/shop_images\/RUMIANO-Bar-OG_Sharp_Cheddar_Bar-811355002546-8oz-3-4.png",
            "clase_imagen": "Mediano-imagen-multicolumna",
            "block_background_color": "#f5f5f5",
            "transparent_background": true,
            "title": "Bars",
            "clase_subtitulo": "Titulo-Nickson-four-h3",
            "title_color": "#002554",
            "text": "<p>8 Products<\/p>",
            "text_color": "#977233"
          }
        },
        "bloque_multicolumna_9FgWni": {
          "type": "bloque_multicolumna",
          "settings": {
            "top_image": "shopify:\/\/shop_images\/RUMIANO-Slices-Shingles-OGMontereyJackSlices-811355002621-6oz-Front_f14ae5fb-c43b-43f2-8b4b-167e2070bd38.png",
            "clase_imagen": "Mediano-imagen-multicolumna",
            "block_background_color": "#f5f5f5",
            "transparent_background": true,
            "title": "Slices",
            "clase_subtitulo": "Titulo-Nickson-four-h3",
            "title_color": "#002554",
            "text": "<p>8 Products<\/p>",
            "text_color": "#977233"
          }
        },
        "bloque_multicolumna_MfUht6": {
          "type": "bloque_multicolumna",
          "settings": {
            "top_image": "shopify:\/\/shop_images\/RUMIANO-Shreds-OGShreddedMexicanBlend-6oz-811355004052-6oz-Front.png",
            "clase_imagen": "Mediano-imagen-multicolumna",
            "block_background_color": "#f5f5f5",
            "transparent_background": true,
            "title": "Shreds",
            "clase_subtitulo": "Titulo-Nickson-four-h3",
            "title_color": "#002554",
            "text": "<p>8 Products<\/p>",
            "text_color": "#977233"
          }
        },
        "bloque_multicolumna_8NKV49": {
          "type": "bloque_multicolumna",
          "settings": {
            "top_image": "shopify:\/\/shop_images\/RUMIANO-Butter-Organic_Butter_with_Sea_Salt-811355003352-8oz-Front.png",
            "clase_imagen": "Mediano-imagen-multicolumna",
            "block_background_color": "#f5f5f5",
            "transparent_background": true,
            "title": "Butter",
            "clase_subtitulo": "Titulo-Nickson-four-h3",
            "title_color": "#002554",
            "text": "<p>2 Products<\/p>",
            "text_color": "#977233"
          }
        },
        "bloque_multicolumna_LCbcKR": {
          "type": "bloque_multicolumna",
          "settings": {
            "top_image": "shopify:\/\/shop_images\/Queso-isolated.png",
            "clase_imagen": "Mediano-imagen-multicolumna",
            "block_background_color": "#f5f5f5",
            "transparent_background": true,
            "title": "Dips",
            "clase_subtitulo": "Titulo-Nickson-four-h3",
            "title_color": "#002554",
            "text": "<p>2 Products<\/p>",
            "text_color": "#977233"
          }
        }
      },
      "block_order": [
        "bloque_multicolumna_CFeDCx",
        "bloque_multicolumna_9FgWni",
        "bloque_multicolumna_MfUht6",
        "bloque_multicolumna_8NKV49",
        "bloque_multicolumna_LCbcKR"
      ],
      "disabled": true,
      "settings": {
        "background_color": "#eddec1",
        "background_image": "shopify:\/\/shop_images\/Shop-image-5.png",
        "enable_background_image": false,
        "padding_top": 10,
        "padding_sides": 50,
        "columns_desktop": 5,
        "column_gap": 0
      }
    },
    "main_coleccion_de_productos_filtros_CTgfqX": {
      "type": "main-coleccion-de-productos-filtros",
      "disabled": true,
      "settings": {
        "background_color": "#fff9f1",
        "titulo": "Give the Gift of Organic Cheese",
        "clase_titulo": "Titulo-Nickson-four-h1",
        "color_titulo": "#002554",
        "texto": "",
        "color_texto": "#666666",
        "ocultar_botones": true,
        "mostrar_dos_botones": true,
        "texto_boton_1": "See All Products  →",
        "enlace_boton_1": "",
        "color_boton_1": "#002554",
        "color_texto_boton_1": "#ffffff",
        "boton_1_transparente": false,
        "texto_boton_2": "Contact",
        "enlace_boton_2": "",
        "color_boton_2": "#002554",
        "color_texto_boton_2": "#002554",
        "boton_2_transparente": true,
        "collection": "rumiano-holiday",
        "columns": 4,
        "rows": 6,
        "producto-provedor": "#002554",
        "producto-titulo": "#002554",
        "clase_titulo_productos": "Titulo-Nickson-six-h6",
        "producto-categoria": "#c9a76d",
        "color_precio_producto": "#002554",
        "producto-peso": "#002554",
        "color_descripcion_producto": "#666666",
        "color_boton_ver": "#002554",
        "color_texto_boton_ver": "#002554",
        "boton_ver_transparente": true,
        "ocultar_boton_ver": false,
        "texto_boton_wheretobuy": "Where to buy",
        "enlace_boton_wheretobuy": "https:\/\/rumianocheese.com\/pages\/where-to-buy",
        "color_boton_wheretobuy": "#002554",
        "color_texto_boton_wheretobuy": "#ffffff",
        "boton_wheretobuy_transparente": false,
        "color_boton_agregar": "#002554",
        "color_texto_boton_agregar": "#ffffff",
        "boton_agregar_transparente": false,
        "transparent_cards": true,
        "card_background_color": "#f5f5f5",
        "mostrar_filtro_tipo": false,
        "texto_todos": "All",
        "filtro_todos_imagen": "shopify:\/\/shop_images\/All-normal_c4ed06bb-2984-4e38-8255-cadc7e8b09e9.png",
        "filtro_todos_imagen_activa": "shopify:\/\/shop_images\/All_products.png",
        "filtro_manual_1": "Bars",
        "filtro_manual_1_imagen": "shopify:\/\/shop_images\/Bars.png",
        "filtro_manual_1_imagen_activa": "shopify:\/\/shop_images\/Bars-active_2cdab75e-ee00-4b39-b86d-6ca16da4d319.png",
        "filtro_manual_2": "Dips",
        "filtro_manual_2_imagen": "shopify:\/\/shop_images\/Dips.png",
        "filtro_manual_2_imagen_activa": "shopify:\/\/shop_images\/Dip-active.png",
        "filtro_manual_3": "Slices",
        "filtro_manual_3_imagen": "shopify:\/\/shop_images\/Slices.png",
        "filtro_manual_3_imagen_activa": "shopify:\/\/shop_images\/Slices-active.png",
        "filtro_manual_4": "Shreds",
        "filtro_manual_4_imagen": "shopify:\/\/shop_images\/Shreds.png",
        "filtro_manual_4_imagen_activa": "shopify:\/\/shop_images\/shreds-active.png",
        "filtro_manual_5": "Butter",
        "filtro_manual_5_imagen": "shopify:\/\/shop_images\/Butter.png",
        "filtro_manual_5_imagen_activa": "shopify:\/\/shop_images\/butter-active.png",
        "filtro_manual_6": "",
        "filtro_manual_7": ""
      }
    },
    "main_coleccion_de_productos_filtros_BtVDMJ": {
      "type": "main-coleccion-de-productos-filtros",
      "settings": {
        "background_color": "#fff9f1",
        "titulo": "Discover Our Organic Favorites",
        "clase_titulo": "Titulo-Nickson-four-h1",
        "color_titulo": "#002554",
        "texto": "<p>From creamy Havarti to tangy Cheddar, Rumiano Organic offers flavors crafted with care for every occasion.<\/p>",
        "color_texto": "#666666",
        "ocultar_botones": true,
        "mostrar_dos_botones": true,
        "texto_boton_1": "See All Products  →",
        "enlace_boton_1": "",
        "color_boton_1": "#002554",
        "color_texto_boton_1": "#ffffff",
        "boton_1_transparente": false,
        "texto_boton_2": "Contact",
        "enlace_boton_2": "",
        "color_boton_2": "#002554",
        "color_texto_boton_2": "#002554",
        "boton_2_transparente": true,
        "collection": "frontpage",
        "columns": 4,
        "rows": 6,
        "producto-provedor": "#002554",
        "producto-titulo": "#002554",
        "clase_titulo_productos": "Titulo-Nickson-six-h6",
        "producto-categoria": "#c9a76d",
        "color_precio_producto": "#002554",
        "producto-peso": "#002554",
        "color_descripcion_producto": "#666666",
        "color_boton_ver": "#002554",
        "color_texto_boton_ver": "#002554",
        "boton_ver_transparente": true,
        "ocultar_boton_ver": false,
        "texto_boton_wheretobuy": "Where to buy",
        "enlace_boton_wheretobuy": "https:\/\/rumianocheese.com\/pages\/where-to-buy",
        "color_boton_wheretobuy": "#002554",
        "color_texto_boton_wheretobuy": "#ffffff",
        "boton_wheretobuy_transparente": false,
        "color_boton_agregar": "#002554",
        "color_texto_boton_agregar": "#ffffff",
        "boton_agregar_transparente": false,
        "transparent_cards": true,
        "card_background_color": "#f5f5f5",
        "mostrar_filtro_tipo": true,
        "texto_todos": "All",
        "filtro_todos_imagen": "shopify:\/\/shop_images\/All-normal_c4ed06bb-2984-4e38-8255-cadc7e8b09e9.png",
        "filtro_todos_imagen_activa": "shopify:\/\/shop_images\/All_products.png",
        "filtro_manual_1": "Bars",
        "filtro_manual_1_imagen": "shopify:\/\/shop_images\/Bars.png",
        "filtro_manual_1_imagen_activa": "shopify:\/\/shop_images\/Bars-active_2cdab75e-ee00-4b39-b86d-6ca16da4d319.png",
        "filtro_manual_2": "Dips",
        "filtro_manual_2_imagen": "shopify:\/\/shop_images\/Dips.png",
        "filtro_manual_2_imagen_activa": "shopify:\/\/shop_images\/Dip-active.png",
        "filtro_manual_3": "Slices",
        "filtro_manual_3_imagen": "shopify:\/\/shop_images\/Slices.png",
        "filtro_manual_3_imagen_activa": "shopify:\/\/shop_images\/Slices-active.png",
        "filtro_manual_4": "Shreds",
        "filtro_manual_4_imagen": "shopify:\/\/shop_images\/Shreds.png",
        "filtro_manual_4_imagen_activa": "shopify:\/\/shop_images\/shreds-active.png",
        "filtro_manual_5": "Butter",
        "filtro_manual_5_imagen": "shopify:\/\/shop_images\/Butter.png",
        "filtro_manual_5_imagen_activa": "shopify:\/\/shop_images\/butter-active.png",
        "filtro_manual_6": "",
        "filtro_manual_7": ""
      }
    },
    "main_slider_logocarousel_e9MdBQ": {
      "type": "main-slider-logocarousel",
      "blocks": {
        "logo_hRJHmY": {
          "type": "logo",
          "settings": {
            "logo_image": "shopify:\/\/shop_images\/StoreLogo_MomsOrganicMarket.svg",
            "logo_link": ""
          }
        },
        "logo_VfH4PN": {
          "type": "logo",
          "settings": {
            "logo_image": "shopify:\/\/shop_images\/StoreLogo_FreshThyme.svg",
            "logo_link": ""
          }
        },
        "logo_MjpGLE": {
          "type": "logo",
          "settings": {
            "logo_image": "shopify:\/\/shop_images\/StoreLogo_LazyAcres.svg",
            "logo_link": ""
          }
        },
        "logo_Ky6qig": {
          "type": "logo",
          "settings": {
            "logo_image": "shopify:\/\/shop_images\/StoreLogo_Sprouts.svg",
            "logo_link": ""
          }
        },
        "logo_rYY9yX": {
          "type": "logo",
          "settings": {
            "logo_image": "shopify:\/\/shop_images\/StoreLogo_NaturalGroceries.svg",
            "logo_link": ""
          }
        },
        "logo_Jc7GaP": {
          "type": "logo",
          "settings": {
            "logo_image": "shopify:\/\/shop_images\/StoreLogo_WholeFoods.svg",
            "logo_link": ""
          }
        }
      },
      "block_order": [
        "logo_hRJHmY",
        "logo_VfH4PN",
        "logo_MjpGLE",
        "logo_Ky6qig",
        "logo_rYY9yX",
        "logo_Jc7GaP"
      ],
      "name": "Infinite Logo Slider",
      "settings": {
        "background_color": "#002554",
        "enable_background_image": false,
        "title": "Find us at",
        "title_font": "Titulo-Nickson-four-h1",
        "title_color": "#fafbfc",
        "padding_top": 40,
        "padding_bottom": 40,
        "padding_sides": 0,
        "logo_spacing": 10,
        "logo_width": 15,
        "animation_speed": 30,
        "animation_speed_mobile": 120,
        "pause_on_hover": false
      }
    },
    "main_coleccion_de_prodcutos_custom_qrVTj3": {
      "type": "main-coleccion-de-prodcutos-custom",
      "disabled": true,
      "settings": {
        "title": "Productos Destacados",
        "collection": "frontpage",
        "products_per_page": 6,
        "columns": 3
      }
    },
    "main_coleccion_de_productos_Tj8a6Q": {
      "type": "main-coleccion-de-productos",
      "disabled": true,
      "settings": {
        "background_color": "#fff9f1",
        "titulo": "Rumiano Merch",
        "clase_titulo": "Titulo-Nickson-four-h1",
        "color_titulo": "#002554",
        "texto": "<p>Get a comfy way to represent your favorite family cheese company in style with Rumiano branded merchandise.<\/p>",
        "color_texto": "#002554",
        "ocultar_botones": true,
        "mostrar_dos_botones": false,
        "texto_boton_1": "See All Products  →",
        "enlace_boton_1": "",
        "color_boton_1": "#002554",
        "color_texto_boton_1": "#ffffff",
        "boton_1_transparente": false,
        "texto_boton_2": "Contact",
        "enlace_boton_2": "",
        "color_boton_2": "#002554",
        "color_texto_boton_2": "#002554",
        "boton_2_transparente": true,
        "collection": "rumiano-gear",
        "columns": 3,
        "rows": 1,
        "producto-provedor": "#002554",
        "producto-titulo": "#002554",
        "clase_titulo_productos": "Titulo-Nickson-six-h6",
        "producto-categoria": "#c9a76d",
        "color_precio_producto": "#002554",
        "producto-peso": "#002554",
        "color_descripcion_producto": "#666666",
        "color_boton_ver": "#002554",
        "color_texto_boton_ver": "#002554",
        "boton_ver_transparente": true,
        "ocultar_boton_ver": true,
        "texto_boton_wheretobuy": "Where to buy",
        "text_button_addtocart": "Add to Cart",
        "enlace_boton_wheretobuy": "",
        "color_boton_wheretobuy": "#002554",
        "color_texto_boton_wheretobuy": "#ffffff",
        "boton_wheretobuy_transparente": false,
        "color_boton_agregar": "#002554",
        "color_texto_boton_agregar": "#ffffff",
        "boton_agregar_transparente": false,
        "transparent_cards": true,
        "card_background_color": "#f5f5f5"
      }
    }
  },
  "order": [
    "main",
    "main_portada_unicolumna_xwrrPf",
    "main_coleccion_de_productos_Jc3pRG",
    "main_slider_animado_logos_eDDnQ3",
    "main_contenedor_titular_cuerpo_unicolumna_dQfyUk",
    "main_contenedor_multicolumnas_bloques_wbjfPR",
    "main_coleccion_de_productos_filtros_CTgfqX",
    "main_coleccion_de_productos_filtros_BtVDMJ",
    "main_slider_logocarousel_e9MdBQ",
    "main_coleccion_de_prodcutos_custom_qrVTj3",
    "main_coleccion_de_productos_Tj8a6Q"
  ]
}
